subclrschm/__init__.py
subclrschm/__main__.py
subclrschm/lib/__init__.py
subclrschm/lib/__meta__.py
subclrschm/lib/__version__.py
subclrschm/lib/default_new_theme.py
subclrschm/lib/parse_args.py
subclrschm/lib/rgba.py
subclrschm/lib/util.py
subclrschm/lib/x11colors.py
subclrschm/lib/gui/__init__.py
subclrschm/lib/gui/about_dialog.py
subclrschm/lib/gui/basic_dialogs.py
subclrschm/lib/gui/color_setting_dialog.py
subclrschm/lib/gui/custom_app.py
subclrschm/lib/gui/custom_statusbar.py
subclrschm/lib/gui/global_setting_dialog.py
subclrschm/lib/gui/global_settings_panel.py
subclrschm/lib/gui/grid_helper.py
subclrschm/lib/gui/gui.py
subclrschm/lib/gui/messages.py
subclrschm/lib/gui/platform_window_focus.py
subclrschm/lib/gui/settings_codes.py
subclrschm/lib/gui/settings_key_bindings.py
subclrschm/lib/gui/simplelog.py
subclrschm/lib/gui/style_settings_panel.py
subclrschm/lib/gui/subclrschm_app.py
subclrschm/lib/gui/data/__init__.py
subclrschm/lib/gui/data/floppy.png
subclrschm/lib/gui/data/subclrschm.icns
subclrschm/lib/gui/data/subclrschm.ico
subclrschm/lib/gui/data/subclrschm.png
subclrschm/lib/gui/data/subclrschm_dialog.png
subclrschm/lib/gui/data/subclrschm_hires.png
subclrschm/lib/gui/data/subclrschm_large.png
subclrschm-2.1.3.dist-info/DESCRIPTION.rst
subclrschm-2.1.3.dist-info/METADATA
subclrschm-2.1.3.dist-info/RECORD
subclrschm-2.1.3.dist-info/WHEEL
subclrschm-2.1.3.dist-info/entry_points.txt
subclrschm-2.1.3.dist-info/metadata.json
subclrschm-2.1.3.dist-info/top_level.txt
