Metadata-Version: 2.0
Name: subclrschm
Version: 2.1.3
Summary: GUI for editing Sublime Text color schemes.
Home-page: https://github.com/facelessuser/subclrschm
Author: Isaac Muse
Author-email: Isaac.Muse@gmail.com
License: MIT License
Keywords: Sublime color scheme
Platform: UNKNOWN
Classifier: Development Status :: 5 - Production/Stable
Classifier: Environment :: Console
Classifier: Intended Audience :: Developers
Classifier: License :: OSI Approved :: MIT License
Classifier: Operating System :: OS Independent
Classifier: Programming Language :: Python :: 2
Classifier: Programming Language :: Python :: 2.7
Classifier: Programming Language :: Python :: 3
Classifier: Programming Language :: Python :: 3.4
Classifier: Programming Language :: Python :: 3.5
Classifier: Programming Language :: Python :: 3.6
Classifier: Topic :: Software Development :: Libraries :: Python Modules
Requires-Dist: wxpython (>=4.0.0a3)
